Workbook
Name PropertyList: Properties!$A$3:$A$14
Name CategoryList: Lists!$A$2:$A$14
Name PaymentList: Lists!$B$2:$B$6

Sheet Master Expense Log
A1: MASTER EXPENSE LOG — enter every expense here (one row = one expense)
A2: 46025 | B2: 123 Maple St | C2: Cleaning Expenses | D2: SparkleClean Co | E2: Move-out deep clean | F2: 185 | G2: Credit Card | H2: RCPT-1001 | I2: Time Spent (hrs) | J2: Hourly Rate | K2: =IF(AND(ISNUMBER(I2),ISNUMBER(J2)),I2*J2,"") | L2: =IF(AND(F2="",K2=""),"",N(F2)+IF(ISNUMBER(K2),K2,0)) | M2: Tenant turnover
A3: 46027 | B3: 123 Maple St | C3: Repairs | D3: Ace Hardware | E3: Replace kitchen faucet | F3: 92.45 | G3: Credit Card | H3: RCPT-1002 | I3: 1.5 | J3: 45 | K3: =IF(AND(ISNUMBER(I3),ISNUMBER(J3)),I3*J3,"") | L3: =IF(AND(F3="",K3=""),"",N(F3)+IF(ISNUMBER(K3),K3,0)) | M3: Parts + own labor
A4: 46030 | B4: 456 Oak Ave | C4: Utilities | D4: City Water Dept | E4: Water/sewer Dec | F4: 78.2 | G4: Bank Transfer | H4: RCPT-1003 | K4: =IF(AND(ISNUMBER(I4),ISNUMBER(J4)),I4*J4,"") | L4: =IF(AND(F4="",K4=""),"",N(F4)+IF(ISNUMBER(K4),K4,0))
A5: 46031 | B5: 789 Pine Rd | C5: Property Management Fees | D5: Summit PM | E5: Jan management 8% | F5: 140 | G5: Bank Transfer | H5: RCPT-1004 | K5: =IF(AND(ISNUMBER(I5),ISNUMBER(J5)),I5*J5,"") | L5: =IF(AND(F5="",K5=""),"",N(F5)+IF(ISNUMBER(K5),K5,0))
A6: 46034 | B6: 123 Maple St | C6: Supplies | D6: Home Depot | E6: Air filters, light bulbs | F6: 34.18 | G6: Cash | K6: =IF(AND(ISNUMBER(I6),ISNUMBER(J6)),I6*J6,"") | L6: =IF(AND(F6="",K6=""),"",N(F6)+IF(ISNUMBER(K6),K6,0)) | M6: Missing receipt
A7: 46036 | B7: 456 Oak Ave | C7: Maintenance Expenses | D7: GreenLawn LLC | E7: Snow removal | F7: 60 | G7: Check | H7: RCPT-1006 | K7: =IF(AND(ISNUMBER(I7),ISNUMBER(J7)),I7*J7,"") | L7: =IF(AND(F7="",K7=""),"",N(F7)+IF(ISNUMBER(K7),K7,0))
A8: 46038 | B8: 789 Pine Rd | C8: Insurance | D8: Allstate | E8: Landlord policy Jan | F8: 96 | G8: Bank Transfer | H8: RCPT-1007 | K8: =IF(AND(ISNUMBER(I8),ISNUMBER(J8)),I8*J8,"") | L8: =IF(AND(F8="",K8=""),"",N(F8)+IF(ISNUMBER(K8),K8,0))
A9: 46042 | B9: 123 Maple St | C9: Advertising Costs | D9: Zillow | E9: Listing promotion | F9: 29.99 | G9: Credit Card | K9: =IF(AND(ISNUMBER(I9),ISNUMBER(J9)),I9*J9,"") | L9: =IF(AND(F9="",K9=""),"",N(F9)+IF(ISNUMBER(K9),K9,0)) | M9: Missing receipt
A10: 46044 | B10: 456 Oak Ave | C10: Repairs | D10: Bob's Plumbing | E10: Leaking pipe repair | F10: 210 | G10: Check | H10: RCPT-1009 | K10: =IF(AND(ISNUMBER(I10),ISNUMBER(J10)),I10*J10,"") | L10: =IF(AND(F10="",K10=""),"",N(F10)+IF(ISNUMBER(K10),K10,0))
A11: 46047 | B11: 789 Pine Rd | C11: Legal and Professional Fees | D11: Nguyen CPA | E11: Tax prep consult | F11: 150 | G11: Bank Transfer | H11: RCPT-1010 | K11: =IF(AND(ISNUMBER(I11),ISNUMBER(J11)),I11*J11,"") | L11: =IF(AND(F11="",K11=""),"",N(F11)+IF(ISNUMBER(K11),K11,0))
A12: 46050 | B12: 123 Maple St | C12: Mortgage Interest | D12: First National Bank | E12: Jan interest portion | F12: 512.33 | G12: Bank Transfer | H12: RCPT-1011 | K12: =IF(AND(ISNUMBER(I12),ISNUMBER(J12)),I12*J12,"") | L12: =IF(AND(F12="",K12=""),"",N(F12)+IF(ISNUMBER(K12),K12,0))
A13: 46052 | B13: 456 Oak Ave | C13: Travel Expenses | D13: Personal Vehicle | E13: Site visit mileage 40mi | F13: 26.8 | G13: Cash | H13: RCPT-1012 | I13: 1 | J13: 30 | K13: =IF(AND(ISNUMBER(I13),ISNUMBER(J13)),I13*J13,"") | L13: =IF(AND(F13="",K13=""),"",N(F13)+IF(ISNUMBER(K13),K13,0)) | M13: IRS mileage
A14: 46055 | B14: 789 Pine Rd | C14: Cleaning Expenses | D14: SparkleClean Co | E14: Common area clean | F14: 110 | G14: Credit Card | H14: RCPT-1013 | K14: =IF(AND(ISNUMBER(I14),ISNUMBER(J14)),I14*J14,"") | L14: =IF(AND(F14="",K14=""),"",N(F14)+IF(ISNUMBER(K14),K14,0))
A15: 46057 | B15: 123 Maple St | C15: Property Taxes | D15: Sangamon County | E15: Q1 property tax | F15: 640 | G15: Bank Transfer | H15: RCPT-1014 | K15: =IF(AND(ISNUMBER(I15),ISNUMBER(J15)),I15*J15,"") | L15: =IF(AND(F15="",K15=""),"",N(F15)+IF(ISNUMBER(K15),K15,0))
A16: 46059 | B16: 456 Oak Ave | C16: Utilities | D16: Alliant Energy | E16: Gas/electric Jan | F16: 134.55 | G16: Bank Transfer | H16: RCPT-1015 | K16: =IF(AND(ISNUMBER(I16),ISNUMBER(J16)),I16*J16,"") | L16: =IF(AND(F16="",K16=""),"",N(F16)+IF(ISNUMBER(K16),K16,0))
A17: 46062 | B17: 789 Pine Rd | C17: Maintenance Expenses | D17: Handyman Joe | E17: HVAC filter + tune | F17: 85 | G17: Check | I17: 2 | J17: 40 | K17: =IF(AND(ISNUMBER(I17),ISNUMBER(J17)),I17*J17,"") | L17: =IF(AND(F17="",K17=""),"",N(F17)+IF(ISNUMBER(K17),K17,0)) | M17: Missing receipt; labor logged
A18: 46064 | B18: 123 Maple St | C18: Repairs | D18: Ace Hardware | E18: Drywall patch materials | F18: 47.6 | G18: Credit Card | H18: RCPT-1017 | I18: 3 | J18: 45 | K18: =IF(AND(ISNUMBER(I18),ISNUMBER(J18)),I18*J18,"") | L18: =IF(AND(F18="",K18=""),"",N(F18)+IF(ISNUMBER(K18),K18,0)) | M18: Self-performed repair
A19: 46067 | B19: 456 Oak Ave | C19: Advertising Costs | D19: Facebook Ads | E19: Vacancy ad campaign | F19: 45 | G19: Credit Card | H19: RCPT-1018 | K19: =IF(AND(ISNUMBER(I19),ISNUMBER(J19)),I19*J19,"") | L19: =IF(AND(F19="",K19=""),"",N(F19)+IF(ISNUMBER(K19),K19,0))
A20: 46070 | B20: 789 Pine Rd | C20: Property Management Fees | D20: Summit PM | E20: Feb management 8% | F20: 140 | G20: Bank Transfer | H20: RCPT-1019 | K20: =IF(AND(ISNUMBER(I20),ISNUMBER(J20)),I20*J20,"") | L20: =IF(AND(F20="",K20=""),"",N(F20)+IF(ISNUMBER(K20),K20,0))
A21: 46073 | B21: 123 Maple St | C21: Supplies | D21: Amazon | E21: Smoke detectors (2) | F21: 38.98 | G21: Credit Card | H21: RCPT-1020 | K21: =IF(AND(ISNUMBER(I21),ISNUMBER(J21)),I21*J21,"") | L21: =IF(AND(F21="",K21=""),"",N(F21)+IF(ISNUMBER(K21),K21,0))
A22: 46076 | B22: 456 Oak Ave | C22: Insurance | D22: State Farm | E22: Landlord policy Feb | F22: 102 | G22: Bank Transfer | H22: RCPT-1021 | K22: =IF(AND(ISNUMBER(I22),ISNUMBER(J22)),I22*J22,"") | L22: =IF(AND(F22="",K22=""),"",N(F22)+IF(ISNUMBER(K22),K22,0))
A23: 46078 | B23: 789 Pine Rd | C23: Other Miscellaneous Expenses | D23: HOA | E23: Condo HOA dues | F23: 220 | G23: Bank Transfer | H23: RCPT-1022 | K23: =IF(AND(ISNUMBER(I23),ISNUMBER(J23)),I23*J23,"") | L23: =IF(AND(F23="",K23=""),"",N(F23)+IF(ISNUMBER(K23),K23,0))
A24: 46080 | B24: 123 Maple St | C24: Mortgage Interest | D24: First National Bank | E24: Feb interest portion | F24: 509.1 | G24: Bank Transfer | H24: RCPT-1023 | K24: =IF(AND(ISNUMBER(I24),ISNUMBER(J24)),I24*J24,"") | L24: =IF(AND(F24="",K24=""),"",N(F24)+IF(ISNUMBER(K24),K24,0))
A25: 46081 | B25: 456 Oak Ave | C25: Cleaning Expenses | D25: SparkleClean Co | E25: Unit B turnover clean | F25: 165 | G25: Check | I25: 4 | J25: 25 | K25: =IF(AND(ISNUMBER(I25),ISNUMBER(J25)),I25*J25,"") | L25: =IF(AND(F25="",K25=""),"",N(F25)+IF(ISNUMBER(K25),K25,0)) | M25: Missing receipt; hrs logged
K26: =IF(AND(ISNUMBER(I26),ISNUMBER(J26)),I26*J26,"") | L26: =IF(AND(F26="",K26=""),"",N(F26)+IF(ISNUMBER(K26),K26,0))
K27: =IF(AND(ISNUMBER(I27),ISNUMBER(J27)),I27*J27,"") | L27: =IF(AND(F27="",K27=""),"",N(F27)+IF(ISNUMBER(K27),K27,0))
K28: =IF(AND(ISNUMBER(I28),ISNUMBER(J28)),I28*J28,"") | L28: =IF(AND(F28="",K28=""),"",N(F28)+IF(ISNUMBER(K28),K28,0))
K29: =IF(AND(ISNUMBER(I29),ISNUMBER(J29)),I29*J29,"") | L29: =IF(AND(F29="",K29=""),"",N(F29)+IF(ISNUMBER(K29),K29,0))
K30: =IF(AND(ISNUMBER(I30),ISNUMBER(J30)),I30*J30,"") | L30: =IF(AND(F30="",K30=""),"",N(F30)+IF(ISNUMBER(K30),K30,0))
K31: =IF(AND(ISNUMBER(I31),ISNUMBER(J31)),I31*J31,"") | L31: =IF(AND(F31="",K31=""),"",N(F31)+IF(ISNUMBER(K31),K31,0))
K32: =IF(AND(ISNUMBER(I32),ISNUMBER(J32)),I32*J32,"") | L32: =IF(AND(F32="",K32=""),"",N(F32)+IF(ISNUMBER(K32),K32,0))
K33: =IF(AND(ISNUMBER(I33),ISNUMBER(J33)),I33*J33,"") | L33: =IF(AND(F33="",K33=""),"",N(F33)+IF(ISNUMBER(K33),K33,0))
K34: =IF(AND(ISNUMBER(I34),ISNUMBER(J34)),I34*J34,"") | L34: =IF(AND(F34="",K34=""),"",N(F34)+IF(ISNUMBER(K34),K34,0))
K35: =IF(AND(ISNUMBER(I35),ISNUMBER(J35)),I35*J35,"") | L35: =IF(AND(F35="",K35=""),"",N(F35)+IF(ISNUMBER(K35),K35,0))
K36: =IF(AND(ISNUMBER(I36),ISNUMBER(J36)),I36*J36,"") | L36: =IF(AND(F36="",K36=""),"",N(F36)+IF(ISNUMBER(K36),K36,0))
K37: =IF(AND(ISNUMBER(I37),ISNUMBER(J37)),I37*J37,"") | L37: =IF(AND(F37="",K37=""),"",N(F37)+IF(ISNUMBER(K37),K37,0))
... K501: =IF(AND(ISNUMBER(I501),ISNUMBER(J501)),I501*J501,"") | L501: =IF(AND(F501="",K501=""),"",N(F501)+IF(ISNUMBER(K501),K501,0))

Sheet Properties
A1: PROPERTIES — master list that drives every dropdown & summary
A2: Property Name/Address | B2: Location | C2: Property Type | D2: Acquired
A3: 123 Maple St | B3: Springfield, IL 62704 | C3: Single-Family | D3: 2019-05-10
A4: 456 Oak Ave | B4: Madison, WI 53703 | C4: Duplex | D4: 2021-08-22
A5: 789 Pine Rd | B5: Boulder, CO 80302 | C5: Condo | D5: 2020-02-15
A16: ➕ To add a property, type it in the next empty row above. It appears automatically in the Master Log dropdown and all summaries (slots reserved to row 14).

Sheet Per-Property Summary
A1: PER-PROPERTY SUMMARY — total cost by category × property (live from Master Log)
A2: Category | B2: =Properties!A3 | C2: =Properties!A4 | D2: =Properties!A5 | E2: =Properties!A6 | F2: =Properties!A7 | G2: =Properties!A8 | H2: =Properties!A9 | I2: =Properties!A10 | J2: =Properties!A11 | K2: =Properties!A12 | L2: =Properties!A13 | M2: =Properties!A14 | N2: TOTAL
A3: Cleaning Expenses | B3: =IF(B$2="","",SUMIFS('Master Expense Log'!$L$2:$L$501,'Master Expense Log'!$C$2:$C$501,$A3,'Master Expense Log'!$B$2:$B$501,B$2)) | C3: =IF(C$2="","",SUMIFS('Master Expense Log'!$L$2:$L$501,'Master Expense Log'!$C$2:$C$501,$A3,'Master Expense Log'!$B$2:$B$501,C$2)) | D3: =IF(D$2="","",SUMIFS('Master Expense Log'!$L$2:$L$501,'Master Expense Log'!$C$2:$C$501,$A3,'Master Expense Log'!$B$2:$B$501,D$2)) | E3: =IF(E$2="","",SUMIFS('Master Expense Log'!$L$2:$L$501,'Master Expense Log'!$C$2:$C$501,$A3,'Master Expense Log'!$B$2:$B$501,E$2)) | F3: =IF(F$2="","",SUMIFS('Master Expense Log'!$L$2:$L$501,'Master Expense Log'!$C$2:$C$501,$A3,'Master Expense Log'!$B$2:$B$501,F$2)) | G3: =IF(G$2="","",SUMIFS('Master Expense Log'!$L$2:$L$501,'Master Expense Log'!$C$2:$C$501,$A3,'Master Expense Log'!$B$2:$B$501,G$2)) | H3: =IF(H$2="","",SUMIFS('Master Expense Log'!$L$2:$L$501,'Master Expense Log'!$C$2:$C$501,$A3,'Master Expense Log'!$B$2:$B$501,H$2)) | I3: =IF(I$2="","",SUMIFS('Master Expense Log'!$L$2:$L$501,'Master Expense Log'!$C$2:$C$501,$A3,'Master Expense Log'!$B$2:$B$501,I$2)) | ... M3: =IF(M$2="","",SUMIFS('Master Expense Log'!$L$2:$L$501,'Master Expense Log'!$C$2:$C$501,$A3,'Master Expense Log'!$B$2:$B$501,M$2)) | N3: =SUM(B3:M3)
A4: Maintenance Expenses | B4: =IF(B$2="","",SUMIFS('Master Expense Log'!$L$2:$L$501,'Master Expense Log'!$C$2:$C$501,$A4,'Master Expense Log'!$B$2:$B$501,B$2)) | C4: =IF(C$2="","",SUMIFS('Master Expense Log'!$L$2:$L$501,'Master Expense Log'!$C$2:$C$501,$A4,'Master Expense Log'!$B$2:$B$501,C$2)) | D4: =IF(D$2="","",SUMIFS('Master Expense Log'!$L$2:$L$501,'Master Expense Log'!$C$2:$C$501,$A4,'Master Expense Log'!$B$2:$B$501,D$2)) | E4: =IF(E$2="","",SUMIFS('Master Expense Log'!$L$2:$L$501,'Master Expense Log'!$C$2:$C$501,$A4,'Master Expense Log'!$B$2:$B$501,E$2)) | F4: =IF(F$2="","",SUMIFS('Master Expense Log'!$L$2:$L$501,'Master Expense Log'!$C$2:$C$501,$A4,'Master Expense Log'!$B$2:$B$501,F$2)) | G4: =IF(G$2="","",SUMIFS('Master Expense Log'!$L$2:$L$501,'Master Expense Log'!$C$2:$C$501,$A4,'Master Expense Log'!$B$2:$B$501,G$2)) | H4: =IF(H$2="","",SUMIFS('Master Expense Log'!$L$2:$L$501,'Master Expense Log'!$C$2:$C$501,$A4,'Master Expense Log'!$B$2:$B$501,H$2)) | I4: =IF(I$2="","",SUMIFS('Master Expense Log'!$L$2:$L$501,'Master Expense Log'!$C$2:$C$501,$A4,'Master Expense Log'!$B$2:$B$501,I$2)) | ... M4: =IF(M$2="","",SUMIFS('Master Expense Log'!$L$2:$L$501,'Master Expense Log'!$C$2:$C$501,$A4,'Master Expense Log'!$B$2:$B$501,M$2)) | N4: =SUM(B4:M4)
A5: Repairs | B5: =IF(B$2="","",SUMIFS('Master Expense Log'!$L$2:$L$501,'Master Expense Log'!$C$2:$C$501,$A5,'Master Expense Log'!$B$2:$B$501,B$2)) | C5: =IF(C$2="","",SUMIFS('Master Expense Log'!$L$2:$L$501,'Master Expense Log'!$C$2:$C$501,$A5,'Master Expense Log'!$B$2:$B$501,C$2)) | D5: =IF(D$2="","",SUMIFS('Master Expense Log'!$L$2:$L$501,'Master Expense Log'!$C$2:$C$501,$A5,'Master Expense Log'!$B$2:$B$501,D$2)) | E5: =IF(E$2="","",SUMIFS('Master Expense Log'!$L$2:$L$501,'Master Expense Log'!$C$2:$C$501,$A5,'Master Expense Log'!$B$2:$B$501,E$2)) | F5: =IF(F$2="","",SUMIFS('Master Expense Log'!$L$2:$L$501,'Master Expense Log'!$C$2:$C$501,$A5,'Master Expense Log'!$B$2:$B$501,F$2)) | G5: =IF(G$2="","",SUMIFS('Master Expense Log'!$L$2:$L$501,'Master Expense Log'!$C$2:$C$501,$A5,'Master Expense Log'!$B$2:$B$501,G$2)) | H5: =IF(H$2="","",SUMIFS('Master Expense Log'!$L$2:$L$501,'Master Expense Log'!$C$2:$C$501,$A5,'Master Expense Log'!$B$2:$B$501,H$2)) | I5: =IF(I$2="","",SUMIFS('Master Expense Log'!$L$2:$L$501,'Master Expense Log'!$C$2:$C$501,$A5,'Master Expense Log'!$B$2:$B$501,I$2)) | ... M5: =IF(M$2="","",SUMIFS('Master Expense Log'!$L$2:$L$501,'Master Expense Log'!$C$2:$C$501,$A5,'Master Expense Log'!$B$2:$B$501,M$2)) | N5: =SUM(B5:M5)
A6: Property Management Fees | B6: =IF(B$2="","",SUMIFS('Master Expense Log'!$L$2:$L$501,'Master Expense Log'!$C$2:$C$501,$A6,'Master Expense Log'!$B$2:$B$501,B$2)) | C6: =IF(C$2="","",SUMIFS('Master Expense Log'!$L$2:$L$501,'Master Expense Log'!$C$2:$C$501,$A6,'Master Expense Log'!$B$2:$B$501,C$2)) | D6: =IF(D$2="","",SUMIFS('Master Expense Log'!$L$2:$L$501,'Master Expense Log'!$C$2:$C$501,$A6,'Master Expense Log'!$B$2:$B$501,D$2)) | E6: =IF(E$2="","",SUMIFS('Master Expense Log'!$L$2:$L$501,'Master Expense Log'!$C$2:$C$501,$A6,'Master Expense Log'!$B$2:$B$501,E$2)) | F6: =IF(F$2="","",SUMIFS('Master Expense Log'!$L$2:$L$501,'Master Expense Log'!$C$2:$C$501,$A6,'Master Expense Log'!$B$2:$B$501,F$2)) | G6: =IF(G$2="","",SUMIFS('Master Expense Log'!$L$2:$L$501,'Master Expense Log'!$C$2:$C$501,$A6,'Master Expense Log'!$B$2:$B$501,G$2)) | H6: =IF(H$2="","",SUMIFS('Master Expense Log'!$L$2:$L$501,'Master Expense Log'!$C$2:$C$501,$A6,'Master Expense Log'!$B$2:$B$501,H$2)) | I6: =IF(I$2="","",SUMIFS('Master Expense Log'!$L$2:$L$501,'Master Expense Log'!$C$2:$C$501,$A6,'Master Expense Log'!$B$2:$B$501,I$2)) | ... M6: =IF(M$2="","",SUMIFS('Master Expense Log'!$L$2:$L$501,'Master Expense Log'!$C$2:$C$501,$A6,'Master Expense Log'!$B$2:$B$501,M$2)) | N6: =SUM(B6:M6)
A7: Advertising Costs | B7: =IF(B$2="","",SUMIFS('Master Expense Log'!$L$2:$L$501,'Master Expense Log'!$C$2:$C$501,$A7,'Master Expense Log'!$B$2:$B$501,B$2)) | C7: =IF(C$2="","",SUMIFS('Master Expense Log'!$L$2:$L$501,'Master Expense Log'!$C$2:$C$501,$A7,'Master Expense Log'!$B$2:$B$501,C$2)) | D7: =IF(D$2="","",SUMIFS('Master Expense Log'!$L$2:$L$501,'Master Expense Log'!$C$2:$C$501,$A7,'Master Expense Log'!$B$2:$B$501,D$2)) | E7: =IF(E$2="","",SUMIFS('Master Expense Log'!$L$2:$L$501,'Master Expense Log'!$C$2:$C$501,$A7,'Master Expense Log'!$B$2:$B$501,E$2)) | F7: =IF(F$2="","",SUMIFS('Master Expense Log'!$L$2:$L$501,'Master Expense Log'!$C$2:$C$501,$A7,'Master Expense Log'!$B$2:$B$501,F$2)) | G7: =IF(G$2="","",SUMIFS('Master Expense Log'!$L$2:$L$501,'Master Expense Log'!$C$2:$C$501,$A7,'Master Expense Log'!$B$2:$B$501,G$2)) | H7: =IF(H$2="","",SUMIFS('Master Expense Log'!$L$2:$L$501,'Master Expense Log'!$C$2:$C$501,$A7,'Master Expense Log'!$B$2:$B$501,H$2)) | I7: =IF(I$2="","",SUMIFS('Master Expense Log'!$L$2:$L$501,'Master Expense Log'!$C$2:$C$501,$A7,'Master Expense Log'!$B$2:$B$501,I$2)) | ... M7: =IF(M$2="","",SUMIFS('Master Expense Log'!$L$2:$L$501,'Master Expense Log'!$C$2:$C$501,$A7,'Master Expense Log'!$B$2:$B$501,M$2)) | N7: =SUM(B7:M7)
A8: Utilities | B8: =IF(B$2="","",SUMIFS('Master Expense Log'!$L$2:$L$501,'Master Expense Log'!$C$2:$C$501,$A8,'Master Expense Log'!$B$2:$B$501,B$2)) | C8: =IF(C$2="","",SUMIFS('Master Expense Log'!$L$2:$L$501,'Master Expense Log'!$C$2:$C$501,$A8,'Master Expense Log'!$B$2:$B$501,C$2)) | D8: =IF(D$2="","",SUMIFS('Master Expense Log'!$L$2:$L$501,'Master Expense Log'!$C$2:$C$501,$A8,'Master Expense Log'!$B$2:$B$501,D$2)) | E8: =IF(E$2="","",SUMIFS('Master Expense Log'!$L$2:$L$501,'Master Expense Log'!$C$2:$C$501,$A8,'Master Expense Log'!$B$2:$B$501,E$2)) | F8: =IF(F$2="","",SUMIFS('Master Expense Log'!$L$2:$L$501,'Master Expense Log'!$C$2:$C$501,$A8,'Master Expense Log'!$B$2:$B$501,F$2)) | G8: =IF(G$2="","",SUMIFS('Master Expense Log'!$L$2:$L$501,'Master Expense Log'!$C$2:$C$501,$A8,'Master Expense Log'!$B$2:$B$501,G$2)) | H8: =IF(H$2="","",SUMIFS('Master Expense Log'!$L$2:$L$501,'Master Expense Log'!$C$2:$C$501,$A8,'Master Expense Log'!$B$2:$B$501,H$2)) | I8: =IF(I$2="","",SUMIFS('Master Expense Log'!$L$2:$L$501,'Master Expense Log'!$C$2:$C$501,$A8,'Master Expense Log'!$B$2:$B$501,I$2)) | ... M8: =IF(M$2="","",SUMIFS('Master Expense Log'!$L$2:$L$501,'Master Expense Log'!$C$2:$C$501,$A8,'Master Expense Log'!$B$2:$B$501,M$2)) | N8: =SUM(B8:M8)
A9: Insurance | B9: =IF(B$2="","",SUMIFS('Master Expense Log'!$L$2:$L$501,'Master Expense Log'!$C$2:$C$501,$A9,'Master Expense Log'!$B$2:$B$501,B$2)) | C9: =IF(C$2="","",SUMIFS('Master Expense Log'!$L$2:$L$501,'Master Expense Log'!$C$2:$C$501,$A9,'Master Expense Log'!$B$2:$B$501,C$2)) | D9: =IF(D$2="","",SUMIFS('Master Expense Log'!$L$2:$L$501,'Master Expense Log'!$C$2:$C$501,$A9,'Master Expense Log'!$B$2:$B$501,D$2)) | E9: =IF(E$2="","",SUMIFS('Master Expense Log'!$L$2:$L$501,'Master Expense Log'!$C$2:$C$501,$A9,'Master Expense Log'!$B$2:$B$501,E$2)) | F9: =IF(F$2="","",SUMIFS('Master Expense Log'!$L$2:$L$501,'Master Expense Log'!$C$2:$C$501,$A9,'Master Expense Log'!$B$2:$B$501,F$2)) | G9: =IF(G$2="","",SUMIFS('Master Expense Log'!$L$2:$L$501,'Master Expense Log'!$C$2:$C$501,$A9,'Master Expense Log'!$B$2:$B$501,G$2)) | H9: =IF(H$2="","",SUMIFS('Master Expense Log'!$L$2:$L$501,'Master Expense Log'!$C$2:$C$501,$A9,'Master Expense Log'!$B$2:$B$501,H$2)) | I9: =IF(I$2="","",SUMIFS('Master Expense Log'!$L$2:$L$501,'Master Expense Log'!$C$2:$C$501,$A9,'Master Expense Log'!$B$2:$B$501,I$2)) | ... M9: =IF(M$2="","",SUMIFS('Master Expense Log'!$L$2:$L$501,'Master Expense Log'!$C$2:$C$501,$A9,'Master Expense Log'!$B$2:$B$501,M$2)) | N9: =SUM(B9:M9)
A10: Property Taxes | B10: =IF(B$2="","",SUMIFS('Master Expense Log'!$L$2:$L$501,'Master Expense Log'!$C$2:$C$501,$A10,'Master Expense Log'!$B$2:$B$501,B$2)) | C10: =IF(C$2="","",SUMIFS('Master Expense Log'!$L$2:$L$501,'Master Expense Log'!$C$2:$C$501,$A10,'Master Expense Log'!$B$2:$B$501,C$2)) | D10: =IF(D$2="","",SUMIFS('Master Expense Log'!$L$2:$L$501,'Master Expense Log'!$C$2:$C$501,$A10,'Master Expense Log'!$B$2:$B$501,D$2)) | E10: =IF(E$2="","",SUMIFS('Master Expense Log'!$L$2:$L$501,'Master Expense Log'!$C$2:$C$501,$A10,'Master Expense Log'!$B$2:$B$501,E$2)) | F10: =IF(F$2="","",SUMIFS('Master Expense Log'!$L$2:$L$501,'Master Expense Log'!$C$2:$C$501,$A10,'Master Expense Log'!$B$2:$B$501,F$2)) | G10: =IF(G$2="","",SUMIFS('Master Expense Log'!$L$2:$L$501,'Master Expense Log'!$C$2:$C$501,$A10,'Master Expense Log'!$B$2:$B$501,G$2)) | H10: =IF(H$2="","",SUMIFS('Master Expense Log'!$L$2:$L$501,'Master Expense Log'!$C$2:$C$501,$A10,'Master Expense Log'!$B$2:$B$501,H$2)) | I10: =IF(I$2="","",SUMIFS('Master Expense Log'!$L$2:$L$501,'Master Expense Log'!$C$2:$C$501,$A10,'Master Expense Log'!$B$2:$B$501,I$2)) | ... M10: =IF(M$2="","",SUMIFS('Master Expense Log'!$L$2:$L$501,'Master Expense Log'!$C$2:$C$501,$A10,'Master Expense Log'!$B$2:$B$501,M$2)) | N10: =SUM(B10:M10)
A11: Mortgage Interest | B11: =IF(B$2="","",SUMIFS('Master Expense Log'!$L$2:$L$501,'Master Expense Log'!$C$2:$C$501,$A11,'Master Expense Log'!$B$2:$B$501,B$2)) | C11: =IF(C$2="","",SUMIFS('Master Expense Log'!$L$2:$L$501,'Master Expense Log'!$C$2:$C$501,$A11,'Master Expense Log'!$B$2:$B$501,C$2)) | D11: =IF(D$2="","",SUMIFS('Master Expense Log'!$L$2:$L$501,'Master Expense Log'!$C$2:$C$501,$A11,'Master Expense Log'!$B$2:$B$501,D$2)) | E11: =IF(E$2="","",SUMIFS('Master Expense Log'!$L$2:$L$501,'Master Expense Log'!$C$2:$C$501,$A11,'Master Expense Log'!$B$2:$B$501,E$2)) | F11: =IF(F$2="","",SUMIFS('Master Expense Log'!$L$2:$L$501,'Master Expense Log'!$C$2:$C$501,$A11,'Master Expense Log'!$B$2:$B$501,F$2)) | G11: =IF(G$2="","",SUMIFS('Master Expense Log'!$L$2:$L$501,'Master Expense Log'!$C$2:$C$501,$A11,'Master Expense Log'!$B$2:$B$501,G$2)) | H11: =IF(H$2="","",SUMIFS('Master Expense Log'!$L$2:$L$501,'Master Expense Log'!$C$2:$C$501,$A11,'Master Expense Log'!$B$2:$B$501,H$2)) | I11: =IF(I$2="","",SUMIFS('Master Expense Log'!$L$2:$L$501,'Master Expense Log'!$C$2:$C$501,$A11,'Master Expense Log'!$B$2:$B$501,I$2)) | ... M11: =IF(M$2="","",SUMIFS('Master Expense Log'!$L$2:$L$501,'Master Expense Log'!$C$2:$C$501,$A11,'Master Expense Log'!$B$2:$B$501,M$2)) | N11: =SUM(B11:M11)
A12: Legal and Professional Fees | B12: =IF(B$2="","",SUMIFS('Master Expense Log'!$L$2:$L$501,'Master Expense Log'!$C$2:$C$501,$A12,'Master Expense Log'!$B$2:$B$501,B$2)) | C12: =IF(C$2="","",SUMIFS('Master Expense Log'!$L$2:$L$501,'Master Expense Log'!$C$2:$C$501,$A12,'Master Expense Log'!$B$2:$B$501,C$2)) | D12: =IF(D$2="","",SUMIFS('Master Expense Log'!$L$2:$L$501,'Master Expense Log'!$C$2:$C$501,$A12,'Master Expense Log'!$B$2:$B$501,D$2)) | E12: =IF(E$2="","",SUMIFS('Master Expense Log'!$L$2:$L$501,'Master Expense Log'!$C$2:$C$501,$A12,'Master Expense Log'!$B$2:$B$501,E$2)) | F12: =IF(F$2="","",SUMIFS('Master Expense Log'!$L$2:$L$501,'Master Expense Log'!$C$2:$C$501,$A12,'Master Expense Log'!$B$2:$B$501,F$2)) | G12: =IF(G$2="","",SUMIFS('Master Expense Log'!$L$2:$L$501,'Master Expense Log'!$C$2:$C$501,$A12,'Master Expense Log'!$B$2:$B$501,G$2)) | H12: =IF(H$2="","",SUMIFS('Master Expense Log'!$L$2:$L$501,'Master Expense Log'!$C$2:$C$501,$A12,'Master Expense Log'!$B$2:$B$501,H$2)) | I12: =IF(I$2="","",SUMIFS('Master Expense Log'!$L$2:$L$501,'Master Expense Log'!$C$2:$C$501,$A12,'Master Expense Log'!$B$2:$B$501,I$2)) | ... M12: =IF(M$2="","",SUMIFS('Master Expense Log'!$L$2:$L$501,'Master Expense Log'!$C$2:$C$501,$A12,'Master Expense Log'!$B$2:$B$501,M$2)) | N12: =SUM(B12:M12)
A13: Supplies | B13: =IF(B$2="","",SUMIFS('Master Expense Log'!$L$2:$L$501,'Master Expense Log'!$C$2:$C$501,$A13,'Master Expense Log'!$B$2:$B$501,B$2)) | C13: =IF(C$2="","",SUMIFS('Master Expense Log'!$L$2:$L$501,'Master Expense Log'!$C$2:$C$501,$A13,'Master Expense Log'!$B$2:$B$501,C$2)) | D13: =IF(D$2="","",SUMIFS('Master Expense Log'!$L$2:$L$501,'Master Expense Log'!$C$2:$C$501,$A13,'Master Expense Log'!$B$2:$B$501,D$2)) | E13: =IF(E$2="","",SUMIFS('Master Expense Log'!$L$2:$L$501,'Master Expense Log'!$C$2:$C$501,$A13,'Master Expense Log'!$B$2:$B$501,E$2)) | F13: =IF(F$2="","",SUMIFS('Master Expense Log'!$L$2:$L$501,'Master Expense Log'!$C$2:$C$501,$A13,'Master Expense Log'!$B$2:$B$501,F$2)) | G13: =IF(G$2="","",SUMIFS('Master Expense Log'!$L$2:$L$501,'Master Expense Log'!$C$2:$C$501,$A13,'Master Expense Log'!$B$2:$B$501,G$2)) | H13: =IF(H$2="","",SUMIFS('Master Expense Log'!$L$2:$L$501,'Master Expense Log'!$C$2:$C$501,$A13,'Master Expense Log'!$B$2:$B$501,H$2)) | I13: =IF(I$2="","",SUMIFS('Master Expense Log'!$L$2:$L$501,'Master Expense Log'!$C$2:$C$501,$A13,'Master Expense Log'!$B$2:$B$501,I$2)) | ... M13: =IF(M$2="","",SUMIFS('Master Expense Log'!$L$2:$L$501,'Master Expense Log'!$C$2:$C$501,$A13,'Master Expense Log'!$B$2:$B$501,M$2)) | N13: =SUM(B13:M13)
A14: Travel Expenses | B14: =IF(B$2="","",SUMIFS('Master Expense Log'!$L$2:$L$501,'Master Expense Log'!$C$2:$C$501,$A14,'Master Expense Log'!$B$2:$B$501,B$2)) | C14: =IF(C$2="","",SUMIFS('Master Expense Log'!$L$2:$L$501,'Master Expense Log'!$C$2:$C$501,$A14,'Master Expense Log'!$B$2:$B$501,C$2)) | D14: =IF(D$2="","",SUMIFS('Master Expense Log'!$L$2:$L$501,'Master Expense Log'!$C$2:$C$501,$A14,'Master Expense Log'!$B$2:$B$501,D$2)) | E14: =IF(E$2="","",SUMIFS('Master Expense Log'!$L$2:$L$501,'Master Expense Log'!$C$2:$C$501,$A14,'Master Expense Log'!$B$2:$B$501,E$2)) | F14: =IF(F$2="","",SUMIFS('Master Expense Log'!$L$2:$L$501,'Master Expense Log'!$C$2:$C$501,$A14,'Master Expense Log'!$B$2:$B$501,F$2)) | G14: =IF(G$2="","",SUMIFS('Master Expense Log'!$L$2:$L$501,'Master Expense Log'!$C$2:$C$501,$A14,'Master Expense Log'!$B$2:$B$501,G$2)) | H14: =IF(H$2="","",SUMIFS('Master Expense Log'!$L$2:$L$501,'Master Expense Log'!$C$2:$C$501,$A14,'Master Expense Log'!$B$2:$B$501,H$2)) | I14: =IF(I$2="","",SUMIFS('Master Expense Log'!$L$2:$L$501,'Master Expense Log'!$C$2:$C$501,$A14,'Master Expense Log'!$B$2:$B$501,I$2)) | ... M14: =IF(M$2="","",SUMIFS('Master Expense Log'!$L$2:$L$501,'Master Expense Log'!$C$2:$C$501,$A14,'Master Expense Log'!$B$2:$B$501,M$2)) | N14: =SUM(B14:M14)
A15: Other Miscellaneous Expenses | B15: =IF(B$2="","",SUMIFS('Master Expense Log'!$L$2:$L$501,'Master Expense Log'!$C$2:$C$501,$A15,'Master Expense Log'!$B$2:$B$501,B$2)) | C15: =IF(C$2="","",SUMIFS('Master Expense Log'!$L$2:$L$501,'Master Expense Log'!$C$2:$C$501,$A15,'Master Expense Log'!$B$2:$B$501,C$2)) | D15: =IF(D$2="","",SUMIFS('Master Expense Log'!$L$2:$L$501,'Master Expense Log'!$C$2:$C$501,$A15,'Master Expense Log'!$B$2:$B$501,D$2)) | E15: =IF(E$2="","",SUMIFS('Master Expense Log'!$L$2:$L$501,'Master Expense Log'!$C$2:$C$501,$A15,'Master Expense Log'!$B$2:$B$501,E$2)) | F15: =IF(F$2="","",SUMIFS('Master Expense Log'!$L$2:$L$501,'Master Expense Log'!$C$2:$C$501,$A15,'Master Expense Log'!$B$2:$B$501,F$2)) | G15: =IF(G$2="","",SUMIFS('Master Expense Log'!$L$2:$L$501,'Master Expense Log'!$C$2:$C$501,$A15,'Master Expense Log'!$B$2:$B$501,G$2)) | H15: =IF(H$2="","",SUMIFS('Master Expense Log'!$L$2:$L$501,'Master Expense Log'!$C$2:$C$501,$A15,'Master Expense Log'!$B$2:$B$501,H$2)) | I15: =IF(I$2="","",SUMIFS('Master Expense Log'!$L$2:$L$501,'Master Expense Log'!$C$2:$C$501,$A15,'Master Expense Log'!$B$2:$B$501,I$2)) | ... M15: =IF(M$2="","",SUMIFS('Master Expense Log'!$L$2:$L$501,'Master Expense Log'!$C$2:$C$501,$A15,'Master Expense Log'!$B$2:$B$501,M$2)) | N15: =SUM(B15:M15)
A16: GRAND TOTAL | B16: =SUM(B3:B15) | C16: =SUM(C3:C15) | D16: =SUM(D3:D15) | E16: =SUM(E3:E15) | F16: =SUM(F3:F15) | G16: =SUM(G3:G15) | H16: =SUM(H3:H15) | I16: =SUM(I3:I15) | ... N16: =SUM(N3:N15)

Sheet Annual Tax Summary
A1: ANNUAL TAX SUMMARY
A2: Deductible rental expenses, all properties combined — ready to hand to your accountant.
A4: Tax Year: | B4: 2026 | C4: ◀ change the year; every total below updates automatically
A6: Expense Category | B6: Total Amount | C6: Typically Deductible? | D6: Notes
A7: Cleaning Expenses | B7: =SUMIFS('Master Expense Log'!$L$2:$L$501,'Master Expense Log'!$C$2:$C$501,$A7,'Master Expense Log'!$A$2:$A$501,">="&DATE($B$4,1,1),'Master Expense Log'!$A$2:$A$501,"<="&DATE($B$4,12,31)) | C7: Yes | D7: Schedule E deductible rental expense
A8: Maintenance Expenses | B8: =SUMIFS('Master Expense Log'!$L$2:$L$501,'Master Expense Log'!$C$2:$C$501,$A8,'Master Expense Log'!$A$2:$A$501,">="&DATE($B$4,1,1),'Master Expense Log'!$A$2:$A$501,"<="&DATE($B$4,12,31)) | C8: Yes | D8: Schedule E deductible rental expense
A9: Repairs | B9: =SUMIFS('Master Expense Log'!$L$2:$L$501,'Master Expense Log'!$C$2:$C$501,$A9,'Master Expense Log'!$A$2:$A$501,">="&DATE($B$4,1,1),'Master Expense Log'!$A$2:$A$501,"<="&DATE($B$4,12,31)) | C9: Yes | D9: Schedule E deductible rental expense
A10: Property Management Fees | B10: =SUMIFS('Master Expense Log'!$L$2:$L$501,'Master Expense Log'!$C$2:$C$501,$A10,'Master Expense Log'!$A$2:$A$501,">="&DATE($B$4,1,1),'Master Expense Log'!$A$2:$A$501,"<="&DATE($B$4,12,31)) | C10: Yes | D10: Schedule E deductible rental expense
A11: Advertising Costs | B11: =SUMIFS('Master Expense Log'!$L$2:$L$501,'Master Expense Log'!$C$2:$C$501,$A11,'Master Expense Log'!$A$2:$A$501,">="&DATE($B$4,1,1),'Master Expense Log'!$A$2:$A$501,"<="&DATE($B$4,12,31)) | C11: Yes | D11: Schedule E deductible rental expense
A12: Utilities | B12: =SUMIFS('Master Expense Log'!$L$2:$L$501,'Master Expense Log'!$C$2:$C$501,$A12,'Master Expense Log'!$A$2:$A$501,">="&DATE($B$4,1,1),'Master Expense Log'!$A$2:$A$501,"<="&DATE($B$4,12,31)) | C12: Yes | D12: Schedule E deductible rental expense
A13: Insurance | B13: =SUMIFS('Master Expense Log'!$L$2:$L$501,'Master Expense Log'!$C$2:$C$501,$A13,'Master Expense Log'!$A$2:$A$501,">="&DATE($B$4,1,1),'Master Expense Log'!$A$2:$A$501,"<="&DATE($B$4,12,31)) | C13: Yes | D13: Schedule E deductible rental expense
A14: Property Taxes | B14: =SUMIFS('Master Expense Log'!$L$2:$L$501,'Master Expense Log'!$C$2:$C$501,$A14,'Master Expense Log'!$A$2:$A$501,">="&DATE($B$4,1,1),'Master Expense Log'!$A$2:$A$501,"<="&DATE($B$4,12,31)) | C14: Yes | D14: Schedule E deductible rental expense
A15: Mortgage Interest | B15: =SUMIFS('Master Expense Log'!$L$2:$L$501,'Master Expense Log'!$C$2:$C$501,$A15,'Master Expense Log'!$A$2:$A$501,">="&DATE($B$4,1,1),'Master Expense Log'!$A$2:$A$501,"<="&DATE($B$4,12,31)) | C15: Yes | D15: Schedule E deductible rental expense
A16: Legal and Professional Fees | B16: =SUMIFS('Master Expense Log'!$L$2:$L$501,'Master Expense Log'!$C$2:$C$501,$A16,'Master Expense Log'!$A$2:$A$501,">="&DATE($B$4,1,1),'Master Expense Log'!$A$2:$A$501,"<="&DATE($B$4,12,31)) | C16: Yes | D16: Schedule E deductible rental expense
A17: Supplies | B17: =SUMIFS('Master Expense Log'!$L$2:$L$501,'Master Expense Log'!$C$2:$C$501,$A17,'Master Expense Log'!$A$2:$A$501,">="&DATE($B$4,1,1),'Master Expense Log'!$A$2:$A$501,"<="&DATE($B$4,12,31)) | C17: Yes | D17: Schedule E deductible rental expense
A18: Travel Expenses | B18: =SUMIFS('Master Expense Log'!$L$2:$L$501,'Master Expense Log'!$C$2:$C$501,$A18,'Master Expense Log'!$A$2:$A$501,">="&DATE($B$4,1,1),'Master Expense Log'!$A$2:$A$501,"<="&DATE($B$4,12,31)) | C18: Yes | D18: Schedule E deductible rental expense
A19: Other Miscellaneous Expenses | B19: =SUMIFS('Master Expense Log'!$L$2:$L$501,'Master Expense Log'!$C$2:$C$501,$A19,'Master Expense Log'!$A$2:$A$501,">="&DATE($B$4,1,1),'Master Expense Log'!$A$2:$A$501,"<="&DATE($B$4,12,31)) | C19: Yes | D19: Schedule E deductible rental expense
A20: GRAND TOTAL (all deductible expenses) | B20: =SUM(B7:B19)
A22: Disclaimer: deductibility depends on your facts. Confirm with your CPA. Mortgage interest & property taxes reported on Schedule E.

Sheet Property Detail
A1: PROPERTY DETAIL — pick a property to see all its entries (live from Master Log)
A3: Property: | B3: 123 Maple St | F3: Total Cost: | G3: =SUMIF('Master Expense Log'!$B$2:$B$501,$B$3,'Master Expense Log'!$L$2:$L$501)
F4: Total Hours: | G4: =SUMIF('Master Expense Log'!$B$2:$B$501,$B$3,'Master Expense Log'!$I$2:$I$501)
F5: Labor Cost: | G5: =SUMIF('Master Expense Log'!$B$2:$B$501,$B$3,'Master Expense Log'!$K$2:$K$501)
A6: Category totals for selected property
A7: Cleaning Expenses | B7: =SUMIFS('Master Expense Log'!$L$2:$L$501,'Master Expense Log'!$B$2:$B$501,$B$3,'Master Expense Log'!$C$2:$C$501,$A7)
A8: Maintenance Expenses | B8: =SUMIFS('Master Expense Log'!$L$2:$L$501,'Master Expense Log'!$B$2:$B$501,$B$3,'Master Expense Log'!$C$2:$C$501,$A8)
A9: Repairs | B9: =SUMIFS('Master Expense Log'!$L$2:$L$501,'Master Expense Log'!$B$2:$B$501,$B$3,'Master Expense Log'!$C$2:$C$501,$A9)
A10: Property Management Fees | B10: =SUMIFS('Master Expense Log'!$L$2:$L$501,'Master Expense Log'!$B$2:$B$501,$B$3,'Master Expense Log'!$C$2:$C$501,$A10)
A11: Advertising Costs | B11: =SUMIFS('Master Expense Log'!$L$2:$L$501,'Master Expense Log'!$B$2:$B$501,$B$3,'Master Expense Log'!$C$2:$C$501,$A11)
A12: Utilities | B12: =SUMIFS('Master Expense Log'!$L$2:$L$501,'Master Expense Log'!$B$2:$B$501,$B$3,'Master Expense Log'!$C$2:$C$501,$A12)
A13: Insurance | B13: =SUMIFS('Master Expense Log'!$L$2:$L$501,'Master Expense Log'!$B$2:$B$501,$B$3,'Master Expense Log'!$C$2:$C$501,$A13)
A14: Property Taxes | B14: =SUMIFS('Master Expense Log'!$L$2:$L$501,'Master Expense Log'!$B$2:$B$501,$B$3,'Master Expense Log'!$C$2:$C$501,$A14)
A15: Mortgage Interest | B15: =SUMIFS('Master Expense Log'!$L$2:$L$501,'Master Expense Log'!$B$2:$B$501,$B$3,'Master Expense Log'!$C$2:$C$501,$A15)
A16: Legal and Professional Fees | B16: =SUMIFS('Master Expense Log'!$L$2:$L$501,'Master Expense Log'!$B$2:$B$501,$B$3,'Master Expense Log'!$C$2:$C$501,$A16)
A17: Supplies | B17: =SUMIFS('Master Expense Log'!$L$2:$L$501,'Master Expense Log'!$B$2:$B$501,$B$3,'Master Expense Log'!$C$2:$C$501,$A17)
A18: Travel Expenses | B18: =SUMIFS('Master Expense Log'!$L$2:$L$501,'Master Expense Log'!$B$2:$B$501,$B$3,'Master Expense Log'!$C$2:$C$501,$A18)
A19: Other Miscellaneous Expenses | B19: =SUMIFS('Master Expense Log'!$L$2:$L$501,'Master Expense Log'!$B$2:$B$501,$B$3,'Master Expense Log'!$C$2:$C$501,$A19)
A21: All entries for selected property:
A22: Date | B22: Category | C22: Vendor/Payee | D22: Description | E22: Amount | F22: Receipt Ref # | G22: Total Cost
A23: =IFERROR(FILTER(CHOOSE({1,2,3,4,5,6,7},'Master Expense Log'!A2:A501,'Master Expense Log'!C2:C501,'Master Expense Log'!D2:D501,'Master Expense Log'!E2:E501,'Master Expense Log'!F2:F501,'Master Expense Log'!H2:H501,'Master Expense Log'!L2:L501),'Master Expense Log'!B2:B501=$B$3),"No entries for this property yet."))
A40: This view is READ-ONLY & live. Add / edit / delete entries in the Master Expense Log; this tab updates automatically. (FILTER needs Excel 365 or Google Sheets.)

Sheet Legend & Formula Guide
A1: LEGEND & FORMULA GUIDE
A2: FORMULAS USED
A3: Calculated Labor Cost | B3: =IF(AND(ISNUMBER(hours),ISNUMBER(rate)), hours×rate, "") — labor cost only when BOTH Time Spent and Hourly Rate are filled in; otherwise blank.
A4: Total Cost | B4: =IF(both blank,"", Amount + Labor Cost) — sums the cash amount plus any calculated labor. This is the number every summary uses.
A5: Per-Property Summary | B5: =SUMIFS(Master Total Cost, Category, thisRow, Property, thisColumnHeader) — totals each category for each property. Property headers pull live from the Properties tab.
A6: Annual Tax Summary | B6: =SUMIFS(Master Total Cost, Category, thisRow, Date, >=Jan1 of year, Date, <=Dec31 of year) — totals by category for the year chosen in cell B4.
A7: Property Detail KPIs | B7: =SUMIF(Property, selected, TotalCost / Hours / Labor) — headline totals for the property chosen in B3.
A8: Property Detail table | B8: =FILTER(CHOOSE(...), Property = selected) — spills every matching row live. Needs Excel 365 or Google Sheets (dynamic arrays).
A9: HOW-TO
A10: Add a new property | B10: Go to the Properties tab and type the name in the next empty row (slots reserved through row 14). It appears automatically in every dropdown and summary column.
A11: Add a new expense | B11: Go to Master Expense Log, fill the next empty row. Use the dropdowns for Property, Category, Payment. Labor Cost & Total Cost calculate themselves.
A12: Log labor / your time | B12: Enter Time Spent (hours) AND Hourly Rate on the row — Calculated Labor Cost fills in and rolls into Total Cost automatically.
A13: Run tax summary for a year | B13: Open Annual Tax Summary, change the Tax Year dropdown in cell B4. All category totals + grand total recalculate for that year.
A14: Missing-receipt flag | B14: On the Master Log, any row with an amount/date but a BLANK Receipt Ref # is highlighted amber automatically — chase the receipt before filing.
A15: Export / print tax view | B15: Annual Tax Summary tab → File ▸ Print (print area & fit-to-width are preset) or File ▸ Download / Save As ▸ PDF. Hand the PDF to your accountant.
A16: Upload to Documents | B16: Save/Download this whole workbook (.xlsx) and upload it under Documents to securely share the tax view with your CPA.
A17: TABS
A18: Lists (hidden) | B18: Holds the dropdown source values (categories, payment methods, tax years). Unhide only if you need to edit the master category list.
A19: Properties | B19: Master property list — the single source that drives all dropdowns and summary columns.
A20: Master Expense Log | B20: The one place you enter data. Everything else reads from here.
A21: Per-Property Summary | B21: Category × property matrix, live.
A22: Annual Tax Summary | B22: Printable, year-selectable, accountant-ready view.
A23: Property Detail | B23: Pick one property; see its KPIs, category totals, and full entry list.

Sheet Lists
A1: Expense Categories | B1: Payment Methods | C1: Tax Years
A2: Cleaning Expenses | B2: Cash | C2: 2024
A3: Maintenance Expenses | B3: Check | C3: 2025
A4: Repairs | B4: Credit Card | C4: 2026
A5: Property Management Fees | B5: Bank Transfer | C5: 2027
A6: Advertising Costs | B6: Other | C6: 2028
A7: Utilities
A8: Insurance
A9: Property Taxes
A10: Mortgage Interest
A11: Legal and Professional Fees
A12: Supplies
A13: Travel Expenses
A14: Other Miscellaneous Expenses
